agentuity/__init__.py
agentuity/apis/__init__.py
agentuity/apis/discord.py
agentuity/instrument/__init__.py
agentuity/instrument/httpx_wrap.py
agentuity/instrument/langchain/__init__.py
agentuity/instrument/llamaindex/__init__.py
agentuity/instrument/openai/__init__.py
agentuity/io/__init__.py
agentuity/io/discord.py
agentuity/io/email.py
agentuity/io/telegram.py
agentuity/otel/__init__.py
agentuity/otel/logfilter.py
agentuity/otel/logger.py
agentuity/otel/span_patch.py
agentuity/server/__init__.py
agentuity/server/agent.py
agentuity/server/config.py
agentuity/server/context.py
agentuity/server/data.py
agentuity/server/keyvalue.py
agentuity/server/objectstore.py
agentuity/server/request.py
agentuity/server/response.py
agentuity/server/test_data.py
agentuity/server/types.py
agentuity/server/util.py
agentuity/server/vector.py
agentuity-0.0.106.dist-info/METADATA
agentuity-0.0.106.dist-info/WHEEL
agentuity-0.0.106.dist-info/licenses/LICENSE.md
agentuity-0.0.106.dist-info/RECORD
