Metadata-Version: 2.4
Name: agentuity
Version: 0.0.106
Summary: Agentuity SDK for Python
Project-URL: Homepage, https://agentuity.com
License: Copyright 2025 Agentuity, Inc.
License-File: LICENSE.md
Classifier: License :: OSI Approved :: Apache Software License
Classifier: Operating System :: OS Independent
Classifier: Programming Language :: Python :: 3
Requires-Python: >=3.10
Requires-Dist: aiohttp-sse>=2.2.0
Requires-Dist: aiohttp>=3.11.13
Requires-Dist: asyncio>=3.4.3
Requires-Dist: httpx>=0.28.1
Requires-Dist: mail-parser>=4.1.2
Requires-Dist: openai-agents>=0.0.3
Requires-Dist: opentelemetry-api>=1.31.1
Requires-Dist: opentelemetry-exporter-otlp-proto-http>=1.31.1
Requires-Dist: opentelemetry-exporter-otlp>=1.31.1
Requires-Dist: opentelemetry-instrumentation-httpx>=0.48b0
Requires-Dist: opentelemetry-instrumentation>=0.48b0
Requires-Dist: opentelemetry-sdk>=1.31.1
Requires-Dist: pyyaml>=6.0.2
Requires-Dist: traceloop-sdk>=0.25.0
Requires-Dist: wrapt>=1.17.2
Provides-Extra: dev
Requires-Dist: pytest-asyncio>=0.23.0; extra == 'dev'
Requires-Dist: pytest-mock>=3.11.1; extra == 'dev'
Requires-Dist: pytest>=7.4.0; extra == 'dev'
Requires-Dist: ruff>=0.1.0; extra == 'dev'
